senselink/__init__.py
senselink/__main__.py
senselink/common.py
senselink/data_source.py
senselink/plug_instance.py
senselink/senselink.py
senselink/tplink_encryption.py
senselink/homeassistant/__init__.py
senselink/homeassistant/ha_controller.py
senselink/homeassistant/ha_data_source.py
senselink/mqtt/__init__.py
senselink/mqtt/mqtt_controller.py
senselink/mqtt/mqtt_data_source.py
senselink/mqtt/mqtt_listener.py
SenseLink-2.2.1.dist-info/LICENSE
SenseLink-2.2.1.dist-info/METADATA
SenseLink-2.2.1.dist-info/WHEEL
SenseLink-2.2.1.dist-info/top_level.txt
SenseLink-2.2.1.dist-info/RECORD
