Metadata-Version: 2.1
Name: SenseLink
Version: 2.2.1
Summary: A tool to create virtual smart plugs and inform a Sense Home Energy Monitor about usage in your home
Home-page: https://github.com/cbpowell/SenseLink
Author: Charles Powell
Author-email: cbpowell@gmail.com
License: MIT
Classifier: Programming Language :: Python :: 3.7
Classifier: Programming Language :: Python :: 3.8
Classifier: Programming Language :: Python :: 3.9
License-File: LICENSE
Requires-Dist: aiomqtt ~=1.2
Requires-Dist: dpath ~=2.1
Requires-Dist: paho-mqtt >=1.6.1
Requires-Dist: PyYAML ~=6.0
Requires-Dist: websockets >=10.2
